bigchem/__init__.py
bigchem/algos.py
bigchem/app.py
bigchem/canvas.py
bigchem/config.py
bigchem/py.typed
bigchem/tasks.py
bigchem/utils.py
bigchem-0.10.9.dist-info/METADATA
bigchem-0.10.9.dist-info/WHEEL
bigchem-0.10.9.dist-info/licenses/LICENSE
bigchem-0.10.9.dist-info/RECORD
