Metadata-Version: 2.4
Name: bigchem
Version: 0.10.9
Summary: A distributed system for scaling and parallelizing quantum chemistry calculations
Project-URL: Homepage, https://github.com/mtzgroup/bigchem
Project-URL: Source, https://github.com/mtzgroup/bigchem
Project-URL: Changelog, https://github.com/mtzgroup/bigchem/blob/master/CHANGELOG.md
Project-URL: Bug Tracker, https://github.com/mtzgroup/bigchem/issues
Project-URL: repository, https://github.com/mtzgroup/bigchem
Author-email: Colton Hicks <github@coltonhicks.com>
License: The MIT License (MIT)
License-File: LICENSE
Classifier: Development Status :: 4 - Beta
Classifier: Intended Audience :: Developers
Classifier: Intended Audience :: Science/Research
Classifier: License :: OSI Approved :: MIT License
Classifier: Natural Language :: English
Classifier: Programming Language :: Python :: 3.9
Classifier: Programming Language :: Python :: 3.10
Classifier: Programming Language :: Python :: 3.11
Classifier: Programming Language :: Python :: 3.12
Classifier: Programming Language :: Python :: 3.13
Classifier: Topic :: Scientific/Engineering
Classifier: Topic :: Software Development :: Libraries
Requires-Python: >=3.9
Requires-Dist: celery[redis]<6.0.0,>=5.3.4
Requires-Dist: pydantic-settings<3.0.0,>=2.0.3
Requires-Dist: pydantic<3.0.0,>=2.0.0
Requires-Dist: qcop>=0.10.2
Provides-Extra: all
Requires-Dist: geometric>=1.0.1; extra == 'all'
Requires-Dist: qcengine>=0.28.0; extra == 'all'
Provides-Extra: geometric
Requires-Dist: geometric>=1.0.1; extra == 'geometric'
Provides-Extra: qcengine
Requires-Dist: qcengine>=0.28.0; extra == 'qcengine'
